jlab_enhanced_cell_toolbar/__init__.py
jlab_enhanced_cell_toolbar/_version.py
jlab_enhanced_cell_toolbar/labextension/package.json
jlab_enhanced_cell_toolbar/labextension/schemas/@jlab-enhanced/cell-toolbar/package.json.orig
jlab_enhanced_cell_toolbar/labextension/schemas/@jlab-enhanced/cell-toolbar/plugin.json
jlab_enhanced_cell_toolbar/labextension/static/534.8a5be287833233321974.js
jlab_enhanced_cell_toolbar/labextension/static/986.3df2e43f090fe534735c.js
jlab_enhanced_cell_toolbar/labextension/static/remoteEntry.dd696ead62aa5a50ad65.js
jlab_enhanced_cell_toolbar/labextension/static/style.js
jlab_enhanced_cell_toolbar-3.5.1.data/data/share/jupyter/labextensions/@jlab-enhanced/cell-toolbar/install.json
jlab_enhanced_cell_toolbar-3.5.1.data/data/share/jupyter/labextensions/@jlab-enhanced/cell-toolbar/package.json
jlab_enhanced_cell_toolbar-3.5.1.data/data/share/jupyter/labextensions/@jlab-enhanced/cell-toolbar/schemas/@jlab-enhanced/cell-toolbar/package.json.orig
jlab_enhanced_cell_toolbar-3.5.1.data/data/share/jupyter/labextensions/@jlab-enhanced/cell-toolbar/schemas/@jlab-enhanced/cell-toolbar/plugin.json
jlab_enhanced_cell_toolbar-3.5.1.data/data/share/jupyter/labextensions/@jlab-enhanced/cell-toolbar/static/534.8a5be287833233321974.js
jlab_enhanced_cell_toolbar-3.5.1.data/data/share/jupyter/labextensions/@jlab-enhanced/cell-toolbar/static/986.3df2e43f090fe534735c.js
jlab_enhanced_cell_toolbar-3.5.1.data/data/share/jupyter/labextensions/@jlab-enhanced/cell-toolbar/static/remoteEntry.dd696ead62aa5a50ad65.js
jlab_enhanced_cell_toolbar-3.5.1.data/data/share/jupyter/labextensions/@jlab-enhanced/cell-toolbar/static/style.js
jlab_enhanced_cell_toolbar-3.5.1.dist-info/LICENSE
jlab_enhanced_cell_toolbar-3.5.1.dist-info/METADATA
jlab_enhanced_cell_toolbar-3.5.1.dist-info/WHEEL
jlab_enhanced_cell_toolbar-3.5.1.dist-info/top_level.txt
jlab_enhanced_cell_toolbar-3.5.1.dist-info/RECORD
